sketchup_mcp/__init__.py
sketchup_mcp/__main__.py
sketchup_mcp/server.py
mseep_sketchup_mcp-0.1.21.dist-info/METADATA
mseep_sketchup_mcp-0.1.21.dist-info/WHEEL
mseep_sketchup_mcp-0.1.21.dist-info/entry_points.txt
mseep_sketchup_mcp-0.1.21.dist-info/top_level.txt
mseep_sketchup_mcp-0.1.21.dist-info/RECORD
