Metadata-Version: 2.4
Name: mseep-sketchup-mcp
Version: 0.1.21
Summary: Sketchup integration through Model Context Protocol
Author-email: mseep <support@skydeck.ai>
License: MIT
Project-URL: Homepage, https://github.com/yourusername/sketchup-mcp
Project-URL: Issues, https://github.com/yourusername/sketchup-mcp/issues
Classifier: Programming Language :: Python :: 3
Classifier: License :: OSI Approved :: MIT License
Classifier: Operating System :: OS Independent
Requires-Python: >=3.10
Requires-Dist: mcp[cli]>=1.3.0
